qwc/__init__.py
qwc/client.py
qwc/config.ini
qwc/service.py
qwc/objects/__init__.py
qwc/objects/objects.py
qwc/scripts/start_server.py
qwc-0.0.1.dist-info/LICENSE.txt
qwc-0.0.1.dist-info/METADATA
qwc-0.0.1.dist-info/WHEEL
qwc-0.0.1.dist-info/entry_points.txt
qwc-0.0.1.dist-info/top_level.txt
qwc-0.0.1.dist-info/RECORD
