Metadata-Version: 2.1
Name: qwc
Version: 0.0.1
Summary: 'Middleware for connecting to the Quickbooks Web Connector.'
Home-page: https://github.com/bill-ash/qwc-middleware
Author: Bill Ash
Author-email: bill@overco.net
Project-URL: Bug Tracker, https://github.com/bill-ash/qwc-middleware/issues
Classifier: Programming Language :: Python :: 3
Classifier: License :: OSI Approved :: MIT License
Classifier: Operating System :: OS Independent
Requires-Python: >=3.7
License-File: LICENSE.txt
Requires-Dist: spyne (>=2.0)
Requires-Dist: waitress (>=2.1)
Requires-Dist: walrus (>=0.9)
Requires-Dist: configobj (>=5.0)
Requires-Dist: lxml (>=4.0)
